verboselogs/__init__.py
verboselogs/pylint.py
verboselogs/tests.py
verboselogs-1.6.2.dist-info/DESCRIPTION.rst
verboselogs-1.6.2.dist-info/METADATA
verboselogs-1.6.2.dist-info/RECORD
verboselogs-1.6.2.dist-info/WHEEL
verboselogs-1.6.2.dist-info/metadata.json
verboselogs-1.6.2.dist-info/top_level.txt
